fietsboek/__init__.py
fietsboek/actions.py
fietsboek/alembic/env.py
fietsboek/alembic/script.py.mako
fietsboek/alembic/versions/20220702_1b4b1c179e5a.py
fietsboek/alembic/versions/20220706_c89d9bdbfa68.py
fietsboek/alembic/versions/20220721_091ce24409fe.py
fietsboek/alembic/versions/20220808_d085998b49ca.py
fietsboek/alembic/versions/20221214_c939800af428.py
fietsboek/alembic/versions/20230203_3149aa2d0114.py
fietsboek/alembic/versions/20230830_8f4e4eae5eb2.py
fietsboek/alembic/versions/20230914_4566843039d6.py
fietsboek/alembic/versions/20250607_2ebe1bf66430.py
fietsboek/alembic/versions/README.txt
fietsboek/config.py
fietsboek/convert.py
fietsboek/data.py
fietsboek/email.py
fietsboek/hittekaart.py
fietsboek/jinja2.py
fietsboek/locale/de/DISPLAY_NAME
fietsboek/locale/de/LC_MESSAGES/messages.mo
fietsboek/locale/de/LC_MESSAGES/messages.po
fietsboek/locale/de/html/home.html
fietsboek/locale/en/DISPLAY_NAME
fietsboek/locale/en/LC_MESSAGES/messages.mo
fietsboek/locale/en/LC_MESSAGES/messages.po
fietsboek/locale/en/html/home.html
fietsboek/locale/fietslog.pot
fietsboek/models/__init__.py
fietsboek/models/badge.py
fietsboek/models/comment.py
fietsboek/models/image.py
fietsboek/models/meta.py
fietsboek/models/track.py
fietsboek/models/user.py
fietsboek/pages.py
fietsboek/pshell.py
fietsboek/routes.py
fietsboek/scripts/__init__.py
fietsboek/scripts/fietscron.py
fietsboek/scripts/fietsctl.py
fietsboek/security.py
fietsboek/static/DeadEnd.svg
fietsboek/static/GM_Utils/GPX2GM.css
fietsboek/static/GM_Utils/GPX2GM.js
fietsboek/static/GM_Utils/GPX2GM_Defs.js
fietsboek/static/GM_Utils/Icons/Grau256x256.png
fietsboek/static/GM_Utils/Icons/Loading_icon.gif
fietsboek/static/GM_Utils/Icons/Loading_icon_V1.gif
fietsboek/static/GM_Utils/Icons/Loading_icon_V2.gif
fietsboek/static/GM_Utils/Icons/airport.png
fietsboek/static/GM_Utils/Icons/bar.png
fietsboek/static/GM_Utils/Icons/boat.png
fietsboek/static/GM_Utils/Icons/bridge.png
fietsboek/static/GM_Utils/Icons/castle.png
fietsboek-0.11.0.dist-info/LICENSE.txt
fietsboek-0.11.0.dist-info/METADATA
fietsboek-0.11.0.dist-info/WHEEL
fietsboek-0.11.0.dist-info/entry_points.txt
fietsboek-0.11.0.dist-info/RECORD
