Metadata-Version: 2.3
Name: fietsboek
Version: 0.11.0
Summary: GPX file sharing website
License: AGPL-3.0-or-later
Keywords: web,gpx
Author: Daniel Schadt
Author-email: fietsboek@kingdread.de
Requires-Python: >=3.11,<4.0
Classifier: Development Status :: 3 - Alpha
Classifier: Framework :: Pyramid
Classifier: License :: OSI Approved :: GNU Affero General Public License v3 or later (AGPLv3+)
Classifier: Operating System :: POSIX :: Linux
Classifier: Programming Language :: Python :: 3
Classifier: Programming Language :: Python :: 3.11
Classifier: Programming Language :: Python :: 3.12
Classifier: Programming Language :: Python :: 3.13
Classifier: Topic :: Internet :: WWW/HTTP
Classifier: Topic :: Internet :: WWW/HTTP :: Dynamic Content
Classifier: Topic :: Internet :: WWW/HTTP :: WSGI :: Application
Requires-Dist: Babel (>=2.11,<3.0)
Requires-Dist: Click (>=8.1,<9.0)
Requires-Dist: SQLAlchemy[mypy] (>=2.0.15,<3.0.0)
Requires-Dist: alembic (>=1.8,<2.0)
Requires-Dist: brotli (>=1.0.9,<2.0.0)
Requires-Dist: click-option-group (>=0.5.5,<0.6.0)
Requires-Dist: cryptography (>=45,<46)
Requires-Dist: filelock (>=3.8.2,<4.0.0)
Requires-Dist: fitparse (>=1.2.0,<2.0.0)
Requires-Dist: gpxpy (>=1.5,<2.0)
Requires-Dist: markdown (>=3.4,<4.0)
Requires-Dist: nh3 (>=0.2.9,<0.3.0)
Requires-Dist: pillow (>=11.2.1,<12.0.0)
Requires-Dist: pydantic (>=2,<3)
Requires-Dist: pyramid (>=2,<3)
Requires-Dist: pyramid_debugtoolbar (>=4.9,<5.0)
Requires-Dist: pyramid_jinja2 (>=2.10,<3.0)
Requires-Dist: pyramid_retry (>=2.1,<3.0)
Requires-Dist: pyramid_tm (>=2.5,<3.0)
Requires-Dist: redis (>=6,<7)
Requires-Dist: requests (>=2.28.1,<3.0.0)
Requires-Dist: termcolor (>=3.1.0,<4.0.0)
Requires-Dist: transaction (>=5,<6)
Requires-Dist: waitress (>=3,<4)
Requires-Dist: zope.sqlalchemy (>=3.0,<4.0)
Project-URL: Documentation, https://docs.fietsboek.org/
Project-URL: Homepage, https://fietsboek.org/
Project-URL: Repository, https://gitlab.com/dunj3/fietsboek
